lab4/library.v
  `timescale 1ns/1ps

// ALU Module. Inputs: inA, inB. Output: out. 
// Operations: bitwise and (op = 0)
//             bitwise or  (op = 1)
//             addition (op = 2)
//             subtraction (op = 6)
//             slt  (op = 7)
//             nor (op = 12)
module ALU (out, zero, inA, inB, op);
	parameter	N 		= 32,
				AND		= 4'b0000,
				OR		= 4'b0001,
				ADD		= 4'b0010,
				SUB		= 4'b0110,
				SLT		= 4'b0111,
				NOR		= 4'b1100;

	output reg [N-1:0] out;
	output zero;
	input  [N-1:0] inA, inB;
	input    [3:0] op;

	always @(*)
		begin
			case (op)
				AND:		out = inA & inB;		// bit and
				OR:			out = inA | inB;		// bit or
				ADD: 		out = inA + inB;		// add
				SUB:		out = inA - inB;		// sub
				SLT:		out = (inA < inB)?1:0;	// slt
				NOR:		out = ~(inA | inB);		// nor
				default: 	out = {N{1'bx}};		// no op
			endcase
		end

	assign zero = (out == 0);

endmodule

// Register File Module. Read ports: address raA, data rdA
//                            address raB, data rdB
//                Write port: address wa, data wd, enable wen.
module RegFile (clock, reset, raA, raB, wa, wen, wd, rdA, rdB);
	input clock, reset, wen;
	input [4:0] raA, raB, wa;
	input  [31:0] wd;
	output reg[31:0] rdA, rdB;

	integer i;
	reg [4:0] data[31:0];

	always @(negedge clock, negedge reset)
		begin
			if (~reset)
				for (i = 0; i < 32; i = i + 1) 
					data[i] = 0;
			else begin
				if (wen)
					data[wa] = wd;
				else
					rdA = data[raA];
					rdB = data[raB];
				end
		end

endmodule

lab4/testbench.v
`timescale 1ns/1ps
`define clock_period 2
`include "library.v"

module cpu_tb;

reg       clock, reset;    // Clock and reset signals
reg   [4:0] raA, raB, wa;
reg         wen;
wire   [31:0] wd;
wire  [31:0] rdA, rdB;
integer i;

reg [3:0] op;
wire f_zero;
// Instantiate regfile module
RegFile regs(clock, reset, raA, raB, wa, wen, wd, rdA, rdB);

// YOU ALSO NEED TO INSTATIATE THE ALU HERE 
ALU alu(wd, f_zero, rdA, rdB, op);


initial begin  // Ta statements apo ayto to begin mexri to "end" einai seiriaka
    $dumpfile("wave.vcd");
	$dumpvars(0, cpu_tb);
  // Initialize the module 
   clock = 1'b0;       
   reset = 1'b0;  // Apply reset for a few cycles
   #(4.25*`clock_period) reset = 1'b1;
   
   // Force initialization of the Register File
   for (i = 0; i < 32; i = i+1)
      regs.data[i] = i;   // Note that always R0 = 0 in MIPS 

  // Now apply some inputs. 
  // You SHOULD EXTEND this part of the code with extra inputs
   wen = 0; raA = 32'h1; raB = 32'h13; op = 4'h2;
#(2*`clock_period)
   wa = 32'h1E; wen = 1;
#(2*`clock_period)
   wen = 0; raA = 32'hA; raB = 32'h4; op = 4'h6; 
#(2*`clock_period)
   wa = 32'hE; wen = 1'b1;
#(2*`clock_period)
   wen = 0;
end 

always @(*) begin
   $display ("raA: %d raB: %d rdA: %d rdB: %d wa: %d wen: %d, value: %d", raA, raB, rdA, rdB, wa, wen, regs.data[wa]);
	end

initial
	#80 $finish;
// Generate clock by inverting the signal every half of clock period
always 
   #(`clock_period / 2) clock = ~clock;  

endmodule

lab4/wave.vcd
$date
	Sun Nov  6 18:01:30 2022
$end
$version
	Icarus Verilog
$end
$timescale
	1ps
$end
$scope module cpu_tb $end
$var wire 32 ! wd [31:0] $end
$var wire 32 " rdB [31:0] $end
$var wire 32 # rdA [31:0] $end
$var wire 1 $ f_zero $end
$var reg 1 % clock $end
$var reg 4 & op [3:0] $end
$var reg 5 ' raA [4:0] $end
$var reg 5 ( raB [4:0] $end
$var reg 1 ) reset $end
$var reg 5 * wa [4:0] $end
$var reg 1 + wen $end
$var integer 32 , i [31:0] $end
$scope module alu $end
$var wire 4 - op [3:0] $end
$var wire 1 $ zero $end
$var wire 32 . inB [31:0] $end
$var wire 32 / inA [31:0] $end
$var reg 32 0 out [31:0] $end
$upscope $end
$scope module regs $end
$var wire 1 % clock $end
$var wire 5 1 raA [4:0] $end
$var wire 5 2 raB [4:0] $end
$var wire 1 ) reset $end
$var wire 5 3 wa [4:0] $end
$var wire 32 4 wd [31:0] $end
$var wire 1 + wen $end
$var reg 32 5 rdA [31:0] $end
$var reg 32 6 rdB [31:0] $end
$var integer 32 7 i [31:0] $end
$upscope $end
$upscope $end
$enddefinitions $end
#0
$dumpvars
b100000 7
bx 6
bx 5
bx 4
bx 3
bx 2
bx 1
bx 0
bx /
bx .
bx -
bx ,
x+
bx *
0)
bx (
bx '
bx &
0%
x$
bx #
bx "
bx !
$end
#1000
1%
#2000
b100000 7
0%
#3000
1%
#4000
b100000 7
0%
#5000
1%
#6000
b100000 7
0%
#7000
1%
#8000
b100000 7
0%
#8500
b10 &
b10 -
b10011 (
b10011 2
b1 '
b1 1
0+
b100000 ,
1)
#9000
1%
#10000
0$
b10100 !
b10100 0
b10100 4
b10011 "
b10011 .
b10011 6
b1 #
b1 /
b1 5
0%
#11000
1%
#12000
0%
#12500
1+
b11110 *
b11110 3
#13000
1%
#14000
0%
#15000
1%
#16000
0%
#16500
b11111111111111111111111111101110 !
b11111111111111111111111111101110 0
b11111111111111111111111111101110 4
b110 &
b110 -
b100 (
b100 2
b1010 '
b1010 1
0+
#17000
1%
#18000
b110 !
b110 0
b110 4
b100 "
b100 .
b100 6
b1010 #
b1010 /
b1010 5
0%
#19000
1%
#20000
0%
#20500
1+
b1110 *
b1110 3
#21000
1%
#22000
0%
#23000
1%
#24000
0%
#24500
0+
